.gitignore
AUTHORS
LICENSE
README.md
circle.yml
setup.cfg
setup.py
tox.ini
history/__init__.py
history/logic.py
history/middleware.py
history/storage.py
scrapy_history.egg-info/PKG-INFO
scrapy_history.egg-info/SOURCES.txt
scrapy_history.egg-info/dependency_links.txt
scrapy_history.egg-info/requires.txt
scrapy_history.egg-info/top_level.txt
tests/test_middleware.py